formulite/__init__.py
formulite-0.0.5.dist-info/METADATA
formulite-0.0.5.dist-info/WHEEL
formulite-0.0.5.dist-info/licenses/LICENSE.MIT
formulite-0.0.5.dist-info/RECORD
