Metadata-Version: 2.3
Name: formulite
Version: 0.0.5
Summary: Simple Formula Parser
Project-URL: Repository, https://github.com/Tom-game-project/formulite
License-File: LICENSE.MIT
Keywords: formula,formulite,parser
Requires-Python: >=3.10
